{
  "panels": [
    {
      "datasource": "prometheus",
      "description": "Status of all monitored devices",
      "fieldConfig": {
        "defaults": {
          "color": {
            "mode": "thresholds"
          },
          "mappings": [
            {
              "options": {
                "0": {
                  "color": "red",
                  "index": 0,
                  "text": "❌"  // Cross mark for DOWN
                },
                "1": {
                  "color": "green",
                  "index": 1,
                  "text": "✅"  // Check mark for UP
                }
              },
              "type": "value"
            }
          ],
          "thresholds": {
            "mode": "absolute",
            "steps": [
              {
                "color": "red",
                "value": null
              },
              {
                "color": "green",
                "value": 1
              }
            ]
          },
          "unit": "none"  // Important to show emoji properly
        }
      },
      "gridPos": {
        "h": 7,
        "w": 24,
        "x": 0,
        "y": 0
      },
      "id": 2,
      "options": {
        "colorMode": "value",
        "graphMode": "area",
        "justifyMode": "auto",
        "orientation": "auto",
        "reduceOptions": {
          "calcs": [
            "lastNotNull"
          ],
          "fields": "",
          "values": false
        },
        "textMode": "auto",
        "text": {
          "titleSize": 16,
          "valueSize": 24  // Larger size for emoji
        }
      },
      "targets": [
        {
          "expr": "label_replace(up{job=~\"node|buffalo-nas|juniper-ex2200|paloalto|synology-nas\"}, \"friendly_name\", \"Palo Alto Firewall\", \"instance\", \"10.1.1.1\") or label_replace(up{job=~\"node|buffalo-nas|juniper-ex2200|paloalto|synology-nas\"}, \"friendly_name\", \"Juniper Switch\", \"instance\", \"10.1.1.13\") or label_replace(up{job=~\"node|buffalo-nas|juniper-ex2200|paloalto|synology-nas\"}, \"friendly_name\", \"Buffalo NAS\", \"instance\", \"10.1.1.215\") or label_replace(up{job=~\"node|buffalo-nas|juniper-ex2200|paloalto|synology-nas\"}, \"friendly_name\", \"Home Server\", \"instance\", \"10.1.1.216\") or label_replace(up{job=~\"node|buffalo-nas|juniper-ex2200|paloalto|synology-nas\"}, \"friendly_name\", \"Synology NAS (Primary)\", \"instance\", \"10.1.1.250\") or label_replace(up{job=~\"node|buffalo-nas|juniper-ex2200|paloalto|synology-nas\"}, \"friendly_name\", \"Prometheus Server\", \"instance\", \"10.1.1.251\") or label_replace(up{job=~\"node|buffalo-nas|juniper-ex2200|paloalto|synology-nas\"}, \"friendly_name\", \"Synology NAS (Backup)\", \"instance\", \"10.1.1.253\")",
          "format": "time_series",
          "legendFormat": "{{friendly_name}}",
          "refId": "A"
        }
      ],
      "title": "Device Status",
      "transformations": [
        {
          "id": "filterFieldsByName",
          "options": {
            "include": {
              "names": [
                "Time",
                "Value",
                "friendly_name"
              ]
            }
          }
        }
      ],
      "type": "stat"
    }
  ]
}
